latex_clean_fig/__init__.py
latex_clean_fig/clean.py
latex_clean_fig-0.2.0.dist-info/LICENSE
latex_clean_fig-0.2.0.dist-info/METADATA
latex_clean_fig-0.2.0.dist-info/WHEEL
latex_clean_fig-0.2.0.dist-info/entry_points.txt
latex_clean_fig-0.2.0.dist-info/RECORD
