Metadata-Version: 2.3
Name: latex-clean-fig
Version: 0.2.0
Summary: A CLI tool to clean unused figure files in LaTeX projects
Author: Iztok Fister Jr.
Author-email: iztok@iztok.dev
Requires-Python: >=3.13,<4.0
Classifier: Programming Language :: Python :: 3
Classifier: Programming Language :: Python :: 3.13
Requires-Dist: typer (>=0.20.1,<0.21.0)
